snakemake_logger_plugin_snkmt/__init__.py
snakemake_logger_plugin_snkmt/event_handlers.py
snakemake_logger_plugin_snkmt/log_handler.py
snakemake_logger_plugin_snkmt/parsers.py
snakemake_logger_plugin_snkmt/py.typed
snakemake_logger_plugin_snkmt-0.1.6.dist-info/METADATA
snakemake_logger_plugin_snkmt-0.1.6.dist-info/WHEEL
snakemake_logger_plugin_snkmt-0.1.6.dist-info/licenses/LICENSE
snakemake_logger_plugin_snkmt-0.1.6.dist-info/RECORD
