Metadata-Version: 2.4
Name: snakemake-logger-plugin-snkmt
Version: 0.1.6
Summary: Snakemake logger plugin that writes logs to SQLite database.
Project-URL: repository, https://github.com/cademirch/snakemake-logger-plugin-snkmt
Author-email: Cade Mirchandani <cmirchan@ucsc.edu>
License-File: LICENSE
Requires-Python: <4.0,>=3.11
Requires-Dist: snakemake-interface-logger-plugins<3,>=1.2.0
Requires-Dist: snkmt>=0.2.0
Requires-Dist: sqlalchemy>=2.0.38
